normand/__init__.py
normand/normand.py
normand-0.23.0.dist-info/METADATA
normand-0.23.0.dist-info/WHEEL
normand-0.23.0.dist-info/entry_points.txt
normand-0.23.0.dist-info/RECORD
