Metadata-Version: 2.1
Name: normand
Version: 0.23.0
Summary: Text-to-binary processor with its own language
Home-page: https://github.com/efficios/normand
License: MIT
Keywords: normand,binary
Author: Philippe Proulx
Author-email: eeppeliteloop@gmail.com
Requires-Python: >=3.4,<4.0
Classifier: Development Status :: 3 - Alpha
Classifier: Environment :: Console
Classifier: Intended Audience :: Developers
Classifier: License :: OSI Approved :: MIT License
Classifier: Natural Language :: English
Classifier: Operating System :: OS Independent
Classifier: Programming Language :: Python :: 3
Classifier: Programming Language :: Python :: 3.4
Classifier: Programming Language :: Python :: 3.5
Classifier: Programming Language :: Python :: 3.6
Classifier: Programming Language :: Python :: 3.7
Classifier: Programming Language :: Python :: 3.8
Classifier: Programming Language :: Python :: 3.9
Classifier: Programming Language :: Python :: 3.10
Classifier: Programming Language :: Python :: 3.11
Classifier: Topic :: Software Development :: Compilers
Project-URL: Bug tracker, https://github.com/efficios/normand/issues
Project-URL: Code review, https://review.lttng.org/admin/repos/normand
Project-URL: Repository, https://github.com/efficios/normand
